{
    "/assets/img/sliders/PAUSE-GOURMANDE-1024x392.jpg": "/assets/img/sliders/PAUSE-GOURMANDE-1024x392.jpg",
    "/assets/img/sliders/ECRITURE-1024x392.jpg": "/assets/img/sliders/ECRITURE-1024x392.jpg",
    "/assets/img/sliders/COFFRESTS-ACCESSOIRES-1024x392.jpg": "/assets/img/sliders/COFFRESTS-ACCESSOIRES-1024x392.jpg",
    "/assets/img/sliders/Bureau-events-2023-1024x392.jpg": "/assets/img/sliders/Bureau-events-2023-1024x392.jpg",
    "/assets/img/offres/Offre-spécial-Planet-design-04.png": "/assets/img/offres/Offre-spécial-Planet-design-04.png",
    "/assets/img/offres/Offre-spécial-Planet-design-03.png": "/assets/img/offres/Offre-spécial-Planet-design-03.png",
    "/assets/img/offres/Offre-spécial-Planet-design-02.png": "/assets/img/offres/Offre-spécial-Planet-design-02.png",
    "/assets/img/offres/Offre-spécial-Planet-design-01.png": "/assets/img/offres/Offre-spécial-Planet-design-01.png",
    "/assets/img/offres/Nouvel-arrivage.jpg": "/assets/img/offres/Nouvel-arrivage.jpg",
    "/assets/img/offres/Destockage.png": "/assets/img/offres/Destockage.png",
    "/assets/img/offres/CATALOGUES-2023-1024x449.png": "/assets/img/offres/CATALOGUES-2023-1024x449.png",
    "/assets/img/forces/Ellipse-4.png": "/assets/img/forces/Ellipse-4.png",
    "/assets/img/forces/Ellipse-4-copie.png": "/assets/img/forces/Ellipse-4-copie.png",
    "/assets/img/forces/Ellipse-4-copie-4.png": "/assets/img/forces/Ellipse-4-copie-4.png",
    "/assets/img/forces/Ellipse-4-copie-3.png": "/assets/img/forces/Ellipse-4-copie-3.png",
    "/assets/img/forces/Ellipse-4-copie-2.png": "/assets/img/forces/Ellipse-4-copie-2.png",
    "/assets/img/ecriture/style_plastique/STYLOS-EN-PLASTIQUE.png": "/assets/img/ecriture/style_plastique/STYLOS-EN-PLASTIQUE.png",
    "/assets/img/ecriture/SITE STYLOS EN PLASTIQUE/112142-VR.png": "/assets/img/ecriture/SITE STYLOS EN PLASTIQUE/112142-VR.png",
    "/assets/img/ecriture/SITE STYLOS EN PLASTIQUE/112142-RG.png": "/assets/img/ecriture/SITE STYLOS EN PLASTIQUE/112142-RG.png",
    "/assets/img/ecriture/SITE STYLOS EN PLASTIQUE/112142-NR.png": "/assets/img/ecriture/SITE STYLOS EN PLASTIQUE/112142-NR.png",
    "/assets/img/ecriture/SITE STYLOS EN PLASTIQUE/112142-BL.png": "/assets/img/ecriture/SITE STYLOS EN PLASTIQUE/112142-BL.png",
    "/assets/img/ecriture/SITE STYLOS EN PLASTIQUE/112142-AR.png": "/assets/img/ecriture/SITE STYLOS EN PLASTIQUE/112142-AR.png",
    "/assets/img/ecriture/SITE STYLOS EN PLASTIQUE/112141-VR.png": "/assets/img/ecriture/SITE STYLOS EN PLASTIQUE/112141-VR.png",
    "/assets/img/ecriture/SITE STYLOS EN PLASTIQUE/112141-VI.png": "/assets/img/ecriture/SITE STYLOS EN PLASTIQUE/112141-VI.png",
    "/assets/img/ecriture/SITE STYLOS EN PLASTIQUE/112141-RG.png": "/assets/img/ecriture/SITE STYLOS EN PLASTIQUE/112141-RG.png",
    "/assets/img/ecriture/SITE STYLOS EN PLASTIQUE/112141-OR.png": "/assets/img/ecriture/SITE STYLOS EN PLASTIQUE/112141-OR.png",
    "/assets/img/ecriture/SITE STYLOS EN PLASTIQUE/112141-NR.png": "/assets/img/ecriture/SITE STYLOS EN PLASTIQUE/112141-NR.png",
    "/assets/img/ecriture/SITE STYLOS EN PLASTIQUE/112141-JU.png": "/assets/img/ecriture/SITE STYLOS EN PLASTIQUE/112141-JU.png",
    "/assets/img/ecriture/SITE STYLOS EN PLASTIQUE/112141-BL.png": "/assets/img/ecriture/SITE STYLOS EN PLASTIQUE/112141-BL.png",
    "/assets/img/ecriture/SITE STYLOS EN PLASTIQUE/112141-BC.png": "/assets/img/ecriture/SITE STYLOS EN PLASTIQUE/112141-BC.png",
    "/assets/img/ecriture/SITE STYLOS EN PLASTIQUE/112141-BA.png": "/assets/img/ecriture/SITE STYLOS EN PLASTIQUE/112141-BA.png",
    "/assets/img/ecriture/SITE STYLOS EN PLASTIQUE/112140-VR.png": "/assets/img/ecriture/SITE STYLOS EN PLASTIQUE/112140-VR.png",
    "/assets/img/ecriture/SITE STYLOS EN PLASTIQUE/112140-RG.png": "/assets/img/ecriture/SITE STYLOS EN PLASTIQUE/112140-RG.png",
    "/assets/img/ecriture/SITE STYLOS EN PLASTIQUE/112140-OR.png": "/assets/img/ecriture/SITE STYLOS EN PLASTIQUE/112140-OR.png",
    "/assets/img/ecriture/SITE STYLOS EN PLASTIQUE/112140-NR.png": "/assets/img/ecriture/SITE STYLOS EN PLASTIQUE/112140-NR.png",
    "/assets/img/ecriture/SITE STYLOS EN PLASTIQUE/112140-BL.png": "/assets/img/ecriture/SITE STYLOS EN PLASTIQUE/112140-BL.png",
    "/assets/img/ecriture/SITE STYLOS EN PLASTIQUE/112140-BA.png": "/assets/img/ecriture/SITE STYLOS EN PLASTIQUE/112140-BA.png",
    "/assets/img/ecriture/SITE STYLOS EN PLASTIQUE/112139-VR.png": "/assets/img/ecriture/SITE STYLOS EN PLASTIQUE/112139-VR.png",
    "/assets/img/ecriture/SITE STYLOS EN PLASTIQUE/112139-VI.png": "/assets/img/ecriture/SITE STYLOS EN PLASTIQUE/112139-VI.png",
    "/assets/img/ecriture/SITE STYLOS EN PLASTIQUE/112139-RS.png": "/assets/img/ecriture/SITE STYLOS EN PLASTIQUE/112139-RS.png",
    "/assets/img/ecriture/SITE STYLOS EN PLASTIQUE/112139-RG.png": "/assets/img/ecriture/SITE STYLOS EN PLASTIQUE/112139-RG.png",
    "/assets/img/ecriture/SITE STYLOS EN PLASTIQUE/112139-OR.png": "/assets/img/ecriture/SITE STYLOS EN PLASTIQUE/112139-OR.png",
    "/assets/img/ecriture/SITE STYLOS EN PLASTIQUE/112139-JN.png": "/assets/img/ecriture/SITE STYLOS EN PLASTIQUE/112139-JN.png",
    "/assets/img/ecriture/SITE STYLOS EN PLASTIQUE/112139-BL.png": "/assets/img/ecriture/SITE STYLOS EN PLASTIQUE/112139-BL.png",
    "/assets/img/ecriture/SITE STYLOS EN PLASTIQUE/112138-VR.png": "/assets/img/ecriture/SITE STYLOS EN PLASTIQUE/112138-VR.png",
    "/assets/img/ecriture/SITE STYLOS EN PLASTIQUE/112138-VI.png": "/assets/img/ecriture/SITE STYLOS EN PLASTIQUE/112138-VI.png",
    "/assets/img/ecriture/SITE STYLOS EN PLASTIQUE/112138-RG.png": "/assets/img/ecriture/SITE STYLOS EN PLASTIQUE/112138-RG.png",
    "/assets/img/ecriture/SITE STYLOS EN PLASTIQUE/112138-OR.png": "/assets/img/ecriture/SITE STYLOS EN PLASTIQUE/112138-OR.png",
    "/assets/img/ecriture/SITE STYLOS EN PLASTIQUE/112138-NR.png": "/assets/img/ecriture/SITE STYLOS EN PLASTIQUE/112138-NR.png",
    "/assets/img/ecriture/SITE STYLOS EN PLASTIQUE/112138-JU.png": "/assets/img/ecriture/SITE STYLOS EN PLASTIQUE/112138-JU.png",
    "/assets/img/ecriture/SITE STYLOS EN PLASTIQUE/112138-BL.png": "/assets/img/ecriture/SITE STYLOS EN PLASTIQUE/112138-BL.png",
    "/assets/img/ecriture/SITE STYLOS EN PLASTIQUE/112138-BC.png": "/assets/img/ecriture/SITE STYLOS EN PLASTIQUE/112138-BC.png",
    "/assets/img/ecriture/SITE STYLOS EN PLASTIQUE/112137-VR.png": "/assets/img/ecriture/SITE STYLOS EN PLASTIQUE/112137-VR.png",
    "/assets/img/ecriture/SITE STYLOS EN PLASTIQUE/112137-OR.png": "/assets/img/ecriture/SITE STYLOS EN PLASTIQUE/112137-OR.png",
    "/assets/img/ecriture/SITE STYLOS EN PLASTIQUE/112137-NR.png": "/assets/img/ecriture/SITE STYLOS EN PLASTIQUE/112137-NR.png",
    "/assets/img/ecriture/SITE STYLOS EN PLASTIQUE/112137-BOR.png": "/assets/img/ecriture/SITE STYLOS EN PLASTIQUE/112137-BOR.png",
    "/assets/img/ecriture/SITE STYLOS EN PLASTIQUE/112137-BL.png": "/assets/img/ecriture/SITE STYLOS EN PLASTIQUE/112137-BL.png",
    "/assets/img/ecriture/SITE STYLOS EN PLASTIQUE/112136-VR.png": "/assets/img/ecriture/SITE STYLOS EN PLASTIQUE/112136-VR.png",
    "/assets/img/ecriture/SITE STYLOS EN PLASTIQUE/112136-RG.png": "/assets/img/ecriture/SITE STYLOS EN PLASTIQUE/112136-RG.png",
    "/assets/img/ecriture/SITE STYLOS EN PLASTIQUE/112136-OR.png": "/assets/img/ecriture/SITE STYLOS EN PLASTIQUE/112136-OR.png",
    "/assets/img/ecriture/SITE STYLOS EN PLASTIQUE/112136-JU.png": "/assets/img/ecriture/SITE STYLOS EN PLASTIQUE/112136-JU.png",
    "/assets/img/ecriture/SITE STYLOS EN PLASTIQUE/112136-BL.png": "/assets/img/ecriture/SITE STYLOS EN PLASTIQUE/112136-BL.png",
    "/assets/img/ecriture/SITE STYLOS EN PLASTIQUE/112135-VR.png": "/assets/img/ecriture/SITE STYLOS EN PLASTIQUE/112135-VR.png",
    "/assets/img/ecriture/SITE STYLOS EN PLASTIQUE/112135-OR.png": "/assets/img/ecriture/SITE STYLOS EN PLASTIQUE/112135-OR.png",
    "/assets/img/ecriture/SITE STYLOS EN PLASTIQUE/112135-NR.png": "/assets/img/ecriture/SITE STYLOS EN PLASTIQUE/112135-NR.png",
    "/assets/img/ecriture/SITE STYLOS EN PLASTIQUE/112135-JU.png": "/assets/img/ecriture/SITE STYLOS EN PLASTIQUE/112135-JU.png",
    "/assets/img/ecriture/SITE STYLOS EN PLASTIQUE/112135-BC.png": "/assets/img/ecriture/SITE STYLOS EN PLASTIQUE/112135-BC.png",
    "/assets/img/ecriture/SITE STYLOS EN PLASTIQUE/112135-BA.png": "/assets/img/ecriture/SITE STYLOS EN PLASTIQUE/112135-BA.png",
    "/assets/img/ecriture/SITE STYLOS EN PLASTIQUE/112134-NR.png": "/assets/img/ecriture/SITE STYLOS EN PLASTIQUE/112134-NR.png",
    "/assets/img/ecriture/SITE STYLOS EN PLASTIQUE/112134-AR.png": "/assets/img/ecriture/SITE STYLOS EN PLASTIQUE/112134-AR.png",
    "/assets/img/ecriture/SITE STYLOS EN PLASTIQUE/112133-VR.png": "/assets/img/ecriture/SITE STYLOS EN PLASTIQUE/112133-VR.png",
    "/assets/img/ecriture/SITE STYLOS EN PLASTIQUE/112133-TR.png": "/assets/img/ecriture/SITE STYLOS EN PLASTIQUE/112133-TR.png",
    "/assets/img/ecriture/SITE STYLOS EN PLASTIQUE/112133-OR.png": "/assets/img/ecriture/SITE STYLOS EN PLASTIQUE/112133-OR.png",
    "/assets/img/ecriture/SITE STYLOS EN PLASTIQUE/112133-NR.png": "/assets/img/ecriture/SITE STYLOS EN PLASTIQUE/112133-NR.png",
    "/assets/img/ecriture/SITE STYLOS EN PLASTIQUE/112133-JN.png": "/assets/img/ecriture/SITE STYLOS EN PLASTIQUE/112133-JN.png",
    "/assets/img/ecriture/SITE STYLOS EN PLASTIQUE/112133-BC.png": "/assets/img/ecriture/SITE STYLOS EN PLASTIQUE/112133-BC.png",
    "/assets/img/ecriture/SITE STYLOS EN PLASTIQUE/112133-BA.png": "/assets/img/ecriture/SITE STYLOS EN PLASTIQUE/112133-BA.png",
    "/assets/img/ecriture/SITE STYLOS EN PLASTIQUE/112132-VR.png": "/assets/img/ecriture/SITE STYLOS EN PLASTIQUE/112132-VR.png",
    "/assets/img/ecriture/SITE STYLOS EN PLASTIQUE/112132-RG.png": "/assets/img/ecriture/SITE STYLOS EN PLASTIQUE/112132-RG.png",
    "/assets/img/ecriture/SITE STYLOS EN PLASTIQUE/112132-BL.png": "/assets/img/ecriture/SITE STYLOS EN PLASTIQUE/112132-BL.png",
    "/assets/img/ecriture/SITE STYLOS EN PLASTIQUE/112131-NR.png": "/assets/img/ecriture/SITE STYLOS EN PLASTIQUE/112131-NR.png",
    "/assets/img/ecriture/SITE STYLOS EN PLASTIQUE/112131-BL.png": "/assets/img/ecriture/SITE STYLOS EN PLASTIQUE/112131-BL.png",
    "/assets/img/ecriture/SITE STYLOS EN PLASTIQUE/112130-VI.png": "/assets/img/ecriture/SITE STYLOS EN PLASTIQUE/112130-VI.png",
    "/assets/img/ecriture/SITE STYLOS EN PLASTIQUE/112130-OR.png": "/assets/img/ecriture/SITE STYLOS EN PLASTIQUE/112130-OR.png",
    "/assets/img/ecriture/SITE STYLOS EN PLASTIQUE/112130-JU.png": "/assets/img/ecriture/SITE STYLOS EN PLASTIQUE/112130-JU.png",
    "/assets/img/ecriture/SITE STYLOS EN PLASTIQUE/112130-BL.png": "/assets/img/ecriture/SITE STYLOS EN PLASTIQUE/112130-BL.png",
    "/assets/img/ecriture/SITE STYLOS EN PLASTIQUE/112130-BC.png": "/assets/img/ecriture/SITE STYLOS EN PLASTIQUE/112130-BC.png",
    "/assets/img/ecriture/SITE STYLOS EN PLASTIQUE/112129-VR.png": "/assets/img/ecriture/SITE STYLOS EN PLASTIQUE/112129-VR.png",
    "/assets/img/ecriture/SITE STYLOS EN PLASTIQUE/112129-RS.png": "/assets/img/ecriture/SITE STYLOS EN PLASTIQUE/112129-RS.png",
    "/assets/img/ecriture/SITE STYLOS EN PLASTIQUE/112129-RG.png": "/assets/img/ecriture/SITE STYLOS EN PLASTIQUE/112129-RG.png",
    "/assets/img/ecriture/SITE STYLOS EN PLASTIQUE/112129-OR.png": "/assets/img/ecriture/SITE STYLOS EN PLASTIQUE/112129-OR.png",
    "/assets/img/ecriture/SITE STYLOS EN PLASTIQUE/112129-JU.png": "/assets/img/ecriture/SITE STYLOS EN PLASTIQUE/112129-JU.png",
    "/assets/img/ecriture/SITE STYLOS EN PLASTIQUE/112129-BL.png": "/assets/img/ecriture/SITE STYLOS EN PLASTIQUE/112129-BL.png",
    "/assets/img/ecriture/SITE STYLOS EN PLASTIQUE/112129-BC.png": "/assets/img/ecriture/SITE STYLOS EN PLASTIQUE/112129-BC.png",
    "/assets/img/ecriture/SITE STYLOS EN PLASTIQUE/112128-VR.png": "/assets/img/ecriture/SITE STYLOS EN PLASTIQUE/112128-VR.png",
    "/assets/img/ecriture/SITE STYLOS EN PLASTIQUE/112128-RG.png": "/assets/img/ecriture/SITE STYLOS EN PLASTIQUE/112128-RG.png",
    "/assets/img/ecriture/SITE STYLOS EN PLASTIQUE/112128-OR.png": "/assets/img/ecriture/SITE STYLOS EN PLASTIQUE/112128-OR.png",
    "/assets/img/ecriture/SITE STYLOS EN PLASTIQUE/112128-BL.png": "/assets/img/ecriture/SITE STYLOS EN PLASTIQUE/112128-BL.png",
    "/assets/img/ecriture/SITE STYLOS EN PLASTIQUE/112127-VR.png": "/assets/img/ecriture/SITE STYLOS EN PLASTIQUE/112127-VR.png",
    "/assets/img/ecriture/SITE STYLOS EN PLASTIQUE/112127-RG.png": "/assets/img/ecriture/SITE STYLOS EN PLASTIQUE/112127-RG.png",
    "/assets/img/ecriture/SITE STYLOS EN PLASTIQUE/112127-OR.png": "/assets/img/ecriture/SITE STYLOS EN PLASTIQUE/112127-OR.png",
    "/assets/img/ecriture/SITE STYLOS EN PLASTIQUE/112127-JN.png": "/assets/img/ecriture/SITE STYLOS EN PLASTIQUE/112127-JN.png",
    "/assets/img/ecriture/SITE STYLOS EN PLASTIQUE/112127-BL.png": "/assets/img/ecriture/SITE STYLOS EN PLASTIQUE/112127-BL.png",
    "/assets/img/ecriture/SITE STYLOS EN PLASTIQUE/112126-VR.png": "/assets/img/ecriture/SITE STYLOS EN PLASTIQUE/112126-VR.png",
    "/assets/img/ecriture/SITE STYLOS EN PLASTIQUE/112126-TRS.png": "/assets/img/ecriture/SITE STYLOS EN PLASTIQUE/112126-TRS.png",
    "/assets/img/ecriture/SITE STYLOS EN PLASTIQUE/112126-RG.png": "/assets/img/ecriture/SITE STYLOS EN PLASTIQUE/112126-RG.png",
    "/assets/img/ecriture/SITE STYLOS EN PLASTIQUE/112126-BL.png": "/assets/img/ecriture/SITE STYLOS EN PLASTIQUE/112126-BL.png",
    "/assets/img/ecriture/SITE STYLOS EN PLASTIQUE/112124-VR.png": "/assets/img/ecriture/SITE STYLOS EN PLASTIQUE/112124-VR.png",
    "/assets/img/ecriture/SITE STYLOS EN PLASTIQUE/112124-RG.png": "/assets/img/ecriture/SITE STYLOS EN PLASTIQUE/112124-RG.png",
    "/assets/img/ecriture/SITE STYLOS EN PLASTIQUE/112124-NR.png": "/assets/img/ecriture/SITE STYLOS EN PLASTIQUE/112124-NR.png",
    "/assets/img/ecriture/SITE STYLOS EN PLASTIQUE/112124-BL.png": "/assets/img/ecriture/SITE STYLOS EN PLASTIQUE/112124-BL.png",
    "/assets/img/ecriture/SITE STYLOS EN PLASTIQUE/112124-BA.png": "/assets/img/ecriture/SITE STYLOS EN PLASTIQUE/112124-BA.png",
    "/assets/img/ecriture/SITE STYLOS EN PLASTIQUE/112124-AR.png": "/assets/img/ecriture/SITE STYLOS EN PLASTIQUE/112124-AR.png",
    "/assets/img/ecriture/SITE STYLOS EN PLASTIQUE/112122-VR.png": "/assets/img/ecriture/SITE STYLOS EN PLASTIQUE/112122-VR.png",
    "/assets/img/ecriture/SITE STYLOS EN PLASTIQUE/112122-VI.png": "/assets/img/ecriture/SITE STYLOS EN PLASTIQUE/112122-VI.png",
    "/assets/img/ecriture/SITE STYLOS EN PLASTIQUE/112122-RG.png": "/assets/img/ecriture/SITE STYLOS EN PLASTIQUE/112122-RG.png",
    "/assets/img/ecriture/SITE STYLOS EN PLASTIQUE/112122-OR.png": "/assets/img/ecriture/SITE STYLOS EN PLASTIQUE/112122-OR.png",
    "/assets/img/ecriture/SITE STYLOS EN PLASTIQUE/112122-NR.png": "/assets/img/ecriture/SITE STYLOS EN PLASTIQUE/112122-NR.png",
    "/assets/img/ecriture/SITE STYLOS EN PLASTIQUE/112122-BL.png": "/assets/img/ecriture/SITE STYLOS EN PLASTIQUE/112122-BL.png",
    "/assets/img/ecriture/SITE STYLOS EN PLASTIQUE/112119-VR.png": "/assets/img/ecriture/SITE STYLOS EN PLASTIQUE/112119-VR.png",
    "/assets/img/ecriture/SITE STYLOS EN PLASTIQUE/112119-VP.png": "/assets/img/ecriture/SITE STYLOS EN PLASTIQUE/112119-VP.png",
    "/assets/img/ecriture/SITE STYLOS EN PLASTIQUE/112119-VI.png": "/assets/img/ecriture/SITE STYLOS EN PLASTIQUE/112119-VI.png",
    "/assets/img/ecriture/SITE STYLOS EN PLASTIQUE/112119-RS.png": "/assets/img/ecriture/SITE STYLOS EN PLASTIQUE/112119-RS.png",
    "/assets/img/ecriture/SITE STYLOS EN PLASTIQUE/112119-RG.png": "/assets/img/ecriture/SITE STYLOS EN PLASTIQUE/112119-RG.png",
    "/assets/img/ecriture/SITE STYLOS EN PLASTIQUE/112119-OR.png": "/assets/img/ecriture/SITE STYLOS EN PLASTIQUE/112119-OR.png",
    "/assets/img/ecriture/SITE STYLOS EN PLASTIQUE/112119-NR.png": "/assets/img/ecriture/SITE STYLOS EN PLASTIQUE/112119-NR.png",
    "/assets/img/ecriture/SITE STYLOS EN PLASTIQUE/112119-JN.png": "/assets/img/ecriture/SITE STYLOS EN PLASTIQUE/112119-JN.png",
    "/assets/img/ecriture/SITE STYLOS EN PLASTIQUE/112119-BL.png": "/assets/img/ecriture/SITE STYLOS EN PLASTIQUE/112119-BL.png",
    "/assets/img/ecriture/SITE STYLOS EN PLASTIQUE/112119-BC.png": "/assets/img/ecriture/SITE STYLOS EN PLASTIQUE/112119-BC.png",
    "/assets/img/ecriture/SITE STYLOS EN PLASTIQUE/112119-BA.png": "/assets/img/ecriture/SITE STYLOS EN PLASTIQUE/112119-BA.png",
    "/assets/img/ecriture/SITE STYLOS EN PLASTIQUE/112118-VR.png": "/assets/img/ecriture/SITE STYLOS EN PLASTIQUE/112118-VR.png",
    "/assets/img/ecriture/SITE STYLOS EN PLASTIQUE/112118-VI.png": "/assets/img/ecriture/SITE STYLOS EN PLASTIQUE/112118-VI.png",
    "/assets/img/ecriture/SITE STYLOS EN PLASTIQUE/112118-RG.png": "/assets/img/ecriture/SITE STYLOS EN PLASTIQUE/112118-RG.png",
    "/assets/img/ecriture/SITE STYLOS EN PLASTIQUE/112118-OR.png": "/assets/img/ecriture/SITE STYLOS EN PLASTIQUE/112118-OR.png",
    "/assets/img/ecriture/SITE STYLOS EN PLASTIQUE/112118-NR.png": "/assets/img/ecriture/SITE STYLOS EN PLASTIQUE/112118-NR.png",
    "/assets/img/ecriture/SITE STYLOS EN PLASTIQUE/112118-JN.png": "/assets/img/ecriture/SITE STYLOS EN PLASTIQUE/112118-JN.png",
    "/assets/img/ecriture/SITE STYLOS EN PLASTIQUE/112118-BL.png": "/assets/img/ecriture/SITE STYLOS EN PLASTIQUE/112118-BL.png",
    "/assets/img/ecriture/SITE STYLOS EN PLASTIQUE/112118-BC.png": "/assets/img/ecriture/SITE STYLOS EN PLASTIQUE/112118-BC.png",
    "/assets/img/ecriture/SITE STYLOS EN PLASTIQUE/112116-VR.png": "/assets/img/ecriture/SITE STYLOS EN PLASTIQUE/112116-VR.png",
    "/assets/img/ecriture/SITE STYLOS EN PLASTIQUE/112116-RG.png": "/assets/img/ecriture/SITE STYLOS EN PLASTIQUE/112116-RG.png",
    "/assets/img/ecriture/SITE STYLOS EN PLASTIQUE/112116-OR.png": "/assets/img/ecriture/SITE STYLOS EN PLASTIQUE/112116-OR.png",
    "/assets/img/ecriture/SITE STYLOS EN PLASTIQUE/112116-BL.png": "/assets/img/ecriture/SITE STYLOS EN PLASTIQUE/112116-BL.png",
    "/assets/img/ecriture/SITE STYLOS EN PLASTIQUE/112116-BC.png": "/assets/img/ecriture/SITE STYLOS EN PLASTIQUE/112116-BC.png",
    "/assets/img/ecriture/SITE STYLOS EN PLASTIQUE/112112-VR.png": "/assets/img/ecriture/SITE STYLOS EN PLASTIQUE/112112-VR.png",
    "/assets/img/ecriture/SITE STYLOS EN PLASTIQUE/112112-RG.png": "/assets/img/ecriture/SITE STYLOS EN PLASTIQUE/112112-RG.png",
    "/assets/img/ecriture/SITE STYLOS EN PLASTIQUE/112112-OR.png": "/assets/img/ecriture/SITE STYLOS EN PLASTIQUE/112112-OR.png",
    "/assets/img/ecriture/SITE STYLOS EN PLASTIQUE/112112-JN.png": "/assets/img/ecriture/SITE STYLOS EN PLASTIQUE/112112-JN.png",
    "/assets/img/ecriture/SITE STYLOS EN PLASTIQUE/112112-BL.png": "/assets/img/ecriture/SITE STYLOS EN PLASTIQUE/112112-BL.png",
    "/assets/img/ecriture/SITE STYLOS EN PLASTIQUE/112108-VR.png": "/assets/img/ecriture/SITE STYLOS EN PLASTIQUE/112108-VR.png",
    "/assets/img/ecriture/SITE STYLOS EN PLASTIQUE/112108-VP.png": "/assets/img/ecriture/SITE STYLOS EN PLASTIQUE/112108-VP.png",
    "/assets/img/ecriture/SITE STYLOS EN PLASTIQUE/112108-RS.png": "/assets/img/ecriture/SITE STYLOS EN PLASTIQUE/112108-RS.png",
    "/assets/img/ecriture/SITE STYLOS EN PLASTIQUE/112108-RG.png": "/assets/img/ecriture/SITE STYLOS EN PLASTIQUE/112108-RG.png",
    "/assets/img/ecriture/SITE STYLOS EN PLASTIQUE/112108-OR.png": "/assets/img/ecriture/SITE STYLOS EN PLASTIQUE/112108-OR.png",
    "/assets/img/ecriture/SITE STYLOS EN PLASTIQUE/112108-JN.png": "/assets/img/ecriture/SITE STYLOS EN PLASTIQUE/112108-JN.png",
    "/assets/img/ecriture/SITE STYLOS EN PLASTIQUE/112108-BL.png": "/assets/img/ecriture/SITE STYLOS EN PLASTIQUE/112108-BL.png",
    "/assets/img/ecriture/SITE STYLOS EN PLASTIQUE/112108-BC.png": "/assets/img/ecriture/SITE STYLOS EN PLASTIQUE/112108-BC.png",
    "/assets/img/ecriture/SITE STYLOS EN PLASTIQUE/112108-BA.png": "/assets/img/ecriture/SITE STYLOS EN PLASTIQUE/112108-BA.png",
    "/assets/img/ecriture/SITE STYLOS EN PLASTIQUE/112107-VR.png": "/assets/img/ecriture/SITE STYLOS EN PLASTIQUE/112107-VR.png",
    "/assets/img/ecriture/SITE STYLOS EN PLASTIQUE/112107-RG.png": "/assets/img/ecriture/SITE STYLOS EN PLASTIQUE/112107-RG.png",
    "/assets/img/ecriture/SITE STYLOS EN PLASTIQUE/112107-OR.png": "/assets/img/ecriture/SITE STYLOS EN PLASTIQUE/112107-OR.png",
    "/assets/img/ecriture/SITE STYLOS EN PLASTIQUE/112107-NR.png": "/assets/img/ecriture/SITE STYLOS EN PLASTIQUE/112107-NR.png",
    "/assets/img/ecriture/SITE STYLOS EN PLASTIQUE/112107-JN.png": "/assets/img/ecriture/SITE STYLOS EN PLASTIQUE/112107-JN.png",
    "/assets/img/ecriture/SITE STYLOS EN PLASTIQUE/112107-BL.png": "/assets/img/ecriture/SITE STYLOS EN PLASTIQUE/112107-BL.png",
    "/assets/img/ecriture/SITE STYLOS EN PLASTIQUE/112107-BA.png": "/assets/img/ecriture/SITE STYLOS EN PLASTIQUE/112107-BA.png",
    "/assets/img/ecriture/SITE STYLOS EN PLASTIQUE/112107-AR.png": "/assets/img/ecriture/SITE STYLOS EN PLASTIQUE/112107-AR.png",
    "/assets/img/ecriture/SITE STYLOS EN PLASTIQUE/112106-VR.png": "/assets/img/ecriture/SITE STYLOS EN PLASTIQUE/112106-VR.png",
    "/assets/img/ecriture/SITE STYLOS EN PLASTIQUE/112106-NR.png": "/assets/img/ecriture/SITE STYLOS EN PLASTIQUE/112106-NR.png",
    "/assets/img/ecriture/SITE STYLOS EN PLASTIQUE/112106-BL.png": "/assets/img/ecriture/SITE STYLOS EN PLASTIQUE/112106-BL.png",
    "/assets/img/ecriture/SITE STYLOS EN PLASTIQUE/112106-AR.png": "/assets/img/ecriture/SITE STYLOS EN PLASTIQUE/112106-AR.png",
    "/assets/img/ecriture/SITE STYLOS EN PLASTIQUE/112103-VR.png": "/assets/img/ecriture/SITE STYLOS EN PLASTIQUE/112103-VR.png",
    "/assets/img/ecriture/SITE STYLOS EN PLASTIQUE/112103-RG.png": "/assets/img/ecriture/SITE STYLOS EN PLASTIQUE/112103-RG.png",
    "/assets/img/ecriture/SITE STYLOS EN PLASTIQUE/112103-OR.png": "/assets/img/ecriture/SITE STYLOS EN PLASTIQUE/112103-OR.png",
    "/assets/img/ecriture/SITE STYLOS EN PLASTIQUE/112103-BL.png": "/assets/img/ecriture/SITE STYLOS EN PLASTIQUE/112103-BL.png",
    "/assets/img/ecriture/SITE STYLOS EN PLASTIQUE/112103-BC.png": "/assets/img/ecriture/SITE STYLOS EN PLASTIQUE/112103-BC.png",
    "/assets/img/ecriture/SITE STYLOS EN PLASTIQUE/112102-VR.png": "/assets/img/ecriture/SITE STYLOS EN PLASTIQUE/112102-VR.png",
    "/assets/img/ecriture/SITE STYLOS EN PLASTIQUE/112102-RG.png": "/assets/img/ecriture/SITE STYLOS EN PLASTIQUE/112102-RG.png",
    "/assets/img/ecriture/SITE STYLOS EN PLASTIQUE/112102-OR.png": "/assets/img/ecriture/SITE STYLOS EN PLASTIQUE/112102-OR.png",
    "/assets/img/ecriture/SITE STYLOS EN PLASTIQUE/112102-BL.png": "/assets/img/ecriture/SITE STYLOS EN PLASTIQUE/112102-BL.png",
    "/assets/img/ecriture/SITE STYLOS EN PLASTIQUE/112067-VI.png": "/assets/img/ecriture/SITE STYLOS EN PLASTIQUE/112067-VI.png",
    "/assets/img/ecriture/SITE STYLOS EN PLASTIQUE/112063-VR.png": "/assets/img/ecriture/SITE STYLOS EN PLASTIQUE/112063-VR.png",
    "/assets/img/ecriture/SITE STYLOS EN PLASTIQUE/112063-OR.png": "/assets/img/ecriture/SITE STYLOS EN PLASTIQUE/112063-OR.png",
    "/assets/img/ecriture/SITE STYLOS EN PLASTIQUE/112063-NR.png": "/assets/img/ecriture/SITE STYLOS EN PLASTIQUE/112063-NR.png",
    "/assets/img/ecriture/SITE STYLOS EN PLASTIQUE/112063-BL.png": "/assets/img/ecriture/SITE STYLOS EN PLASTIQUE/112063-BL.png",
    "/assets/img/ecriture/SITE STYLOS EN PLASTIQUE/112063-BC.png": "/assets/img/ecriture/SITE STYLOS EN PLASTIQUE/112063-BC.png",
    "/assets/img/ecriture/SITE STYLOS EN PLASTIQUE/112055-NR.png": "/assets/img/ecriture/SITE STYLOS EN PLASTIQUE/112055-NR.png",
    "/assets/img/ecriture/SITE STYLOS EN PLASTIQUE/112055-GR.png": "/assets/img/ecriture/SITE STYLOS EN PLASTIQUE/112055-GR.png",
    "/assets/img/ecriture/SITE STYLOS EN PLASTIQUE/112055-BA.png": "/assets/img/ecriture/SITE STYLOS EN PLASTIQUE/112055-BA.png",
    "/assets/img/ecriture/SITE STYLOS EN PLASTIQUE/112054-RG.png": "/assets/img/ecriture/SITE STYLOS EN PLASTIQUE/112054-RG.png",
    "/assets/img/ecriture/SITE STYLOS EN PLASTIQUE/112054-NR.png": "/assets/img/ecriture/SITE STYLOS EN PLASTIQUE/112054-NR.png",
    "/assets/img/ecriture/SITE STYLOS EN PLASTIQUE/112054-GR.png": "/assets/img/ecriture/SITE STYLOS EN PLASTIQUE/112054-GR.png",
    "/assets/img/ecriture/SITE STYLOS EN PLASTIQUE/112054-BL.png": "/assets/img/ecriture/SITE STYLOS EN PLASTIQUE/112054-BL.png",
    "/assets/img/ecriture/SITE STYLOS EN PLASTIQUE/112050-VR.png": "/assets/img/ecriture/SITE STYLOS EN PLASTIQUE/112050-VR.png",
    "/assets/img/ecriture/SITE STYLOS EN PLASTIQUE/112050-VI.png": "/assets/img/ecriture/SITE STYLOS EN PLASTIQUE/112050-VI.png",
    "/assets/img/ecriture/SITE STYLOS EN PLASTIQUE/112050-RS.png": "/assets/img/ecriture/SITE STYLOS EN PLASTIQUE/112050-RS.png",
    "/assets/img/ecriture/SITE STYLOS EN PLASTIQUE/112050-RG.png": "/assets/img/ecriture/SITE STYLOS EN PLASTIQUE/112050-RG.png",
    "/assets/img/ecriture/SITE STYLOS EN PLASTIQUE/112050-OR.png": "/assets/img/ecriture/SITE STYLOS EN PLASTIQUE/112050-OR.png",
    "/assets/img/ecriture/SITE STYLOS EN PLASTIQUE/112050-NR.png": "/assets/img/ecriture/SITE STYLOS EN PLASTIQUE/112050-NR.png",
    "/assets/img/ecriture/SITE STYLOS EN PLASTIQUE/112050-JN.png": "/assets/img/ecriture/SITE STYLOS EN PLASTIQUE/112050-JN.png",
    "/assets/img/ecriture/SITE STYLOS EN PLASTIQUE/112050-BL.png": "/assets/img/ecriture/SITE STYLOS EN PLASTIQUE/112050-BL.png",
    "/assets/img/ecriture/SITE STYLOS EN PLASTIQUE/112050-BA.png": "/assets/img/ecriture/SITE STYLOS EN PLASTIQUE/112050-BA.png",
    "/assets/img/ecriture/SITE STYLOS EN PLASTIQUE/112018-JN.jpg": "/assets/img/ecriture/SITE STYLOS EN PLASTIQUE/112018-JN.jpg",
    "/assets/img/ecriture/SITE STYLOS EN PLASTIQUE/112009-VR.png": "/assets/img/ecriture/SITE STYLOS EN PLASTIQUE/112009-VR.png",
    "/assets/img/ecriture/SITE STYLOS EN PLASTIQUE/111018-VR.png": "/assets/img/ecriture/SITE STYLOS EN PLASTIQUE/111018-VR.png",
    "/assets/img/ecriture/SITE STYLOS EN PLASTIQUE/111018-RS.png": "/assets/img/ecriture/SITE STYLOS EN PLASTIQUE/111018-RS.png",
    "/assets/img/ecriture/SITE STYLOS EN PLASTIQUE/Thumbs.db": "/assets/img/ecriture/SITE STYLOS EN PLASTIQUE/Thumbs.db",
    "/assets/img/ecriture/SITE STYLOS EN PLASTIQUE/112147-VR.png": "/assets/img/ecriture/SITE STYLOS EN PLASTIQUE/112147-VR.png",
    "/assets/img/ecriture/SITE STYLOS EN PLASTIQUE/112147-VP.png": "/assets/img/ecriture/SITE STYLOS EN PLASTIQUE/112147-VP.png",
    "/assets/img/ecriture/SITE STYLOS EN PLASTIQUE/112147-VI.png": "/assets/img/ecriture/SITE STYLOS EN PLASTIQUE/112147-VI.png",
    "/assets/img/ecriture/SITE STYLOS EN PLASTIQUE/112147-RS.png": "/assets/img/ecriture/SITE STYLOS EN PLASTIQUE/112147-RS.png",
    "/assets/img/ecriture/SITE STYLOS EN PLASTIQUE/112147-RG.png": "/assets/img/ecriture/SITE STYLOS EN PLASTIQUE/112147-RG.png",
    "/assets/img/ecriture/SITE STYLOS EN PLASTIQUE/112147-OR.png": "/assets/img/ecriture/SITE STYLOS EN PLASTIQUE/112147-OR.png",
    "/assets/img/ecriture/SITE STYLOS EN PLASTIQUE/112147-BL.png": "/assets/img/ecriture/SITE STYLOS EN PLASTIQUE/112147-BL.png",
    "/assets/img/ecriture/SITE STYLOS EN PLASTIQUE/112147-BC.png": "/assets/img/ecriture/SITE STYLOS EN PLASTIQUE/112147-BC.png",
    "/assets/img/ecriture/SITE STYLOS EN PLASTIQUE/112146-VR.png": "/assets/img/ecriture/SITE STYLOS EN PLASTIQUE/112146-VR.png",
    "/assets/img/ecriture/SITE STYLOS EN PLASTIQUE/112146-RG.png": "/assets/img/ecriture/SITE STYLOS EN PLASTIQUE/112146-RG.png",
    "/assets/img/ecriture/SITE STYLOS EN PLASTIQUE/112146-NR.png": "/assets/img/ecriture/SITE STYLOS EN PLASTIQUE/112146-NR.png",
    "/assets/img/ecriture/SITE STYLOS EN PLASTIQUE/112146-BL.png": "/assets/img/ecriture/SITE STYLOS EN PLASTIQUE/112146-BL.png",
    "/assets/img/ecriture/SITE STYLOS EN PLASTIQUE/112145-VR.png": "/assets/img/ecriture/SITE STYLOS EN PLASTIQUE/112145-VR.png",
    "/assets/img/ecriture/SITE STYLOS EN PLASTIQUE/112145-RG.png": "/assets/img/ecriture/SITE STYLOS EN PLASTIQUE/112145-RG.png",
    "/assets/img/ecriture/SITE STYLOS EN PLASTIQUE/112145-NR.png": "/assets/img/ecriture/SITE STYLOS EN PLASTIQUE/112145-NR.png",
    "/assets/img/ecriture/SITE STYLOS EN PLASTIQUE/112145-BL.png": "/assets/img/ecriture/SITE STYLOS EN PLASTIQUE/112145-BL.png",
    "/assets/img/ecriture/SITE STYLOS EN PLASTIQUE/112145-AR.png": "/assets/img/ecriture/SITE STYLOS EN PLASTIQUE/112145-AR.png",
    "/assets/img/ecriture/SITE STYLOS EN PLASTIQUE/112144-VR.png": "/assets/img/ecriture/SITE STYLOS EN PLASTIQUE/112144-VR.png",
    "/assets/img/ecriture/SITE STYLOS EN PLASTIQUE/112144-RG.png": "/assets/img/ecriture/SITE STYLOS EN PLASTIQUE/112144-RG.png",
    "/assets/img/ecriture/SITE STYLOS EN PLASTIQUE/112144-NR.png": "/assets/img/ecriture/SITE STYLOS EN PLASTIQUE/112144-NR.png",
    "/assets/img/ecriture/SITE STYLOS EN PLASTIQUE/112144-BL.png": "/assets/img/ecriture/SITE STYLOS EN PLASTIQUE/112144-BL.png",
    "/assets/img/ecriture/SITE STYLOS EN PLASTIQUE/112144-AR.png": "/assets/img/ecriture/SITE STYLOS EN PLASTIQUE/112144-AR.png",
    "/assets/img/ecriture/SITE STYLOS EN PLASTIQUE/112143-VR.png": "/assets/img/ecriture/SITE STYLOS EN PLASTIQUE/112143-VR.png",
    "/assets/img/ecriture/SITE STYLOS EN PLASTIQUE/112143-VI.png": "/assets/img/ecriture/SITE STYLOS EN PLASTIQUE/112143-VI.png",
    "/assets/img/ecriture/SITE STYLOS EN PLASTIQUE/112143-Turquoise.png": "/assets/img/ecriture/SITE STYLOS EN PLASTIQUE/112143-Turquoise.png",
    "/assets/img/ecriture/SITE STYLOS EN PLASTIQUE/112143-RS.png": "/assets/img/ecriture/SITE STYLOS EN PLASTIQUE/112143-RS.png",
    "/assets/img/ecriture/SITE STYLOS EN PLASTIQUE/112143-RG.png": "/assets/img/ecriture/SITE STYLOS EN PLASTIQUE/112143-RG.png",
    "/assets/img/ecriture/SITE STYLOS EN PLASTIQUE/112143-OR.png": "/assets/img/ecriture/SITE STYLOS EN PLASTIQUE/112143-OR.png",
    "/assets/img/ecriture/SITE STYLOS EN PLASTIQUE/112143-JU.png": "/assets/img/ecriture/SITE STYLOS EN PLASTIQUE/112143-JU.png",
    "/assets/img/ecriture/SITE STYLOS EN PLASTIQUE/112143-BL.png": "/assets/img/ecriture/SITE STYLOS EN PLASTIQUE/112143-BL.png",
    "/assets/img/ecriture/SITE STYLOS EN PLASTIQUE/112143-BC.png": "/assets/img/ecriture/SITE STYLOS EN PLASTIQUE/112143-BC.png",
    "/assets/img/ecriture/SITE STYLOS EN PLASTIQUE/112143-BA.png": "/assets/img/ecriture/SITE STYLOS EN PLASTIQUE/112143-BA.png",
    "/assets/img/ecriture/PL119007-300x300.png": "/assets/img/ecriture/PL119007-300x300.png",
    "/assets/img/ecriture/PL111018-Planet-design-3-300x300.png": "/assets/img/ecriture/PL111018-Planet-design-3-300x300.png",
    "/assets/img/ecriture/Crayons-1.png": "/assets/img/ecriture/Crayons-1.png",
    "/assets/img/ecriture/5.PNG": "/assets/img/ecriture/5.PNG",
    "/assets/img/ecriture/4.PNG": "/assets/img/ecriture/4.PNG",
    "/assets/img/ecriture/3.PNG": "/assets/img/ecriture/3.PNG",
    "/assets/img/ecriture/2.PNG": "/assets/img/ecriture/2.PNG",
    "/assets/img/ecriture/1.PNG": "/assets/img/ecriture/1.PNG",
    "/assets/img/categories/USB-298x447.png": "/assets/img/categories/USB-298x447.png",
    "/assets/img/categories/THERMOS-MUGS-METAL-298x447.png": "/assets/img/categories/THERMOS-MUGS-METAL-298x447.png",
    "/assets/img/categories/TEXTILE-298x447.jpg": "/assets/img/categories/TEXTILE-298x447.jpg",
    "/assets/img/categories/TECHNOLOGIE-298x447.png": "/assets/img/categories/TECHNOLOGIE-298x447.png",
    "/assets/img/categories/Stylo-298x447.png": "/assets/img/categories/Stylo-298x447.png",
    "/assets/img/categories/SANTE-PHARMA-298x447.png": "/assets/img/categories/SANTE-PHARMA-298x447.png",
    "/assets/img/categories/PAUSE-GOURMANDE-298x447.png": "/assets/img/categories/PAUSE-GOURMANDE-298x447.png",
    "/assets/img/categories/NOTE-BOOKS-AGENDAS-298x447.png": "/assets/img/categories/NOTE-BOOKS-AGENDAS-298x447.png",
    "/assets/img/categories/LOISIRS-298x447.png": "/assets/img/categories/LOISIRS-298x447.png",
    "/assets/img/categories/Destockage-298x447.png": "/assets/img/categories/Destockage-298x447.png",
    "/assets/img/categories/COFFRETS-PUBLICITAIRES-298x447.png": "/assets/img/categories/COFFRETS-PUBLICITAIRES-298x447.png",
    "/assets/img/categories/BUREAU-EVENTS-298x447.png": "/assets/img/categories/BUREAU-EVENTS-298x447.png",
    "/assets/img/add2wish.png": "/assets/img/add2wish.png",
    "/assets/img/F1.jpg": "/assets/img/F1.jpg",
    "/assets/img/Add2devis-2.png": "/assets/img/Add2devis-2.png",
    "/assets/img/2.png": "/assets/img/2.png",
    "/css/tom-select.css": "/css/tom-select.css",
    "/css/style.css": "/css/style.css",
    "/css/responsive.css": "/css/responsive.css",
    "/css/owl.theme.default.min.css": "/css/owl.theme.default.min.css",
    "/css/owl.carousel.min.css": "/css/owl.carousel.min.css",
    "/css/jquery-ui.css": "/css/jquery-ui.css",
    "/css/font-awesome-all.min.css": "/css/font-awesome-all.min.css",
    "/css/cdnjs.cloudflare.com_ajax_libs_slick-carousel_1.8.0_slick.min.css": "/css/cdnjs.cloudflare.com_ajax_libs_slick-carousel_1.8.0_slick.min.css",
    "/css/cdnjs.cloudflare.com_ajax_libs_slick-carousel_1.8.0_slick-theme.min.css": "/css/cdnjs.cloudflare.com_ajax_libs_slick-carousel_1.8.0_slick-theme.min.css",
    "/css/app.css": "/css/app.css",
    "/fonts/oswald-font-family/SIL Open Font License.txt": "/fonts/oswald-font-family/SIL Open Font License.txt",
    "/fonts/oswald-font-family/Oswald-Stencil.ttf": "/fonts/oswald-font-family/Oswald-Stencil.ttf",
    "/fonts/oswald-font-family/Oswald-SemiBold.otf": "/fonts/oswald-font-family/Oswald-SemiBold.otf",
    "/fonts/oswald-font-family/Oswald-RegularItalic.ttf": "/fonts/oswald-font-family/Oswald-RegularItalic.ttf",
    "/fonts/oswald-font-family/Oswald-Regular.ttf": "/fonts/oswald-font-family/Oswald-Regular.ttf",
    "/fonts/oswald-font-family/Oswald-Regular.otf": "/fonts/oswald-font-family/Oswald-Regular.otf",
    "/fonts/oswald-font-family/Oswald-MediumItalic.ttf": "/fonts/oswald-font-family/Oswald-MediumItalic.ttf",
    "/fonts/oswald-font-family/Oswald-Medium.ttf": "/fonts/oswald-font-family/Oswald-Medium.ttf",
    "/fonts/oswald-font-family/Oswald-Medium.otf": "/fonts/oswald-font-family/Oswald-Medium.otf",
    "/fonts/oswald-font-family/Oswald-LightItalic.ttf": "/fonts/oswald-font-family/Oswald-LightItalic.ttf",
    "/fonts/oswald-font-family/Oswald-Light.ttf": "/fonts/oswald-font-family/Oswald-Light.ttf",
    "/fonts/oswald-font-family/Oswald-Light.otf": "/fonts/oswald-font-family/Oswald-Light.otf",
    "/fonts/oswald-font-family/Oswald-HeavyItalic.ttf": "/fonts/oswald-font-family/Oswald-HeavyItalic.ttf",
    "/fonts/oswald-font-family/Oswald-Heavy.ttf": "/fonts/oswald-font-family/Oswald-Heavy.ttf",
    "/fonts/oswald-font-family/Oswald-ExtraLight.ttf": "/fonts/oswald-font-family/Oswald-ExtraLight.ttf",
    "/fonts/oswald-font-family/Oswald-ExtraLight.otf": "/fonts/oswald-font-family/Oswald-ExtraLight.otf",
    "/fonts/oswald-font-family/Oswald-Extra-LightItalic.ttf": "/fonts/oswald-font-family/Oswald-Extra-LightItalic.ttf",
    "/fonts/oswald-font-family/Oswald-DemiBold.ttf": "/fonts/oswald-font-family/Oswald-DemiBold.ttf",
    "/fonts/oswald-font-family/Oswald-Demi-BoldItalic.ttf": "/fonts/oswald-font-family/Oswald-Demi-BoldItalic.ttf",
    "/fonts/oswald-font-family/Oswald-BoldItalic.ttf": "/fonts/oswald-font-family/Oswald-BoldItalic.ttf",
    "/fonts/oswald-font-family/Oswald-Bold.ttf": "/fonts/oswald-font-family/Oswald-Bold.ttf",
    "/fonts/oswald-font-family/Oswald-Bold.otf": "/fonts/oswald-font-family/Oswald-Bold.otf",
    "/fonts/Nexa/NexaText-Trial-ThinItalic.otf": "/fonts/Nexa/NexaText-Trial-ThinItalic.otf",
    "/fonts/Nexa/NexaText-Trial-Thin.otf": "/fonts/Nexa/NexaText-Trial-Thin.otf",
    "/fonts/Nexa/NexaText-Trial-RegularItalic.otf": "/fonts/Nexa/NexaText-Trial-RegularItalic.otf",
    "/fonts/Nexa/NexaText-Trial-Regular.otf": "/fonts/Nexa/NexaText-Trial-Regular.otf",
    "/fonts/Nexa/NexaText-Trial-LightItalic.otf": "/fonts/Nexa/NexaText-Trial-LightItalic.otf",
    "/fonts/Nexa/NexaText-Trial-Light.otf": "/fonts/Nexa/NexaText-Trial-Light.otf",
    "/fonts/Nexa/NexaText-Trial-HeavyItalic.otf": "/fonts/Nexa/NexaText-Trial-HeavyItalic.otf",
    "/fonts/Nexa/NexaText-Trial-Heavy.otf": "/fonts/Nexa/NexaText-Trial-Heavy.otf",
    "/fonts/Nexa/NexaText-Trial-ExtraLightItalic.otf": "/fonts/Nexa/NexaText-Trial-ExtraLightItalic.otf",
    "/fonts/Nexa/NexaText-Trial-ExtraLight.otf": "/fonts/Nexa/NexaText-Trial-ExtraLight.otf",
    "/fonts/Nexa/NexaText-Trial-ExtraBoldItalic.otf": "/fonts/Nexa/NexaText-Trial-ExtraBoldItalic.otf",
    "/fonts/Nexa/NexaText-Trial-ExtraBold.otf": "/fonts/Nexa/NexaText-Trial-ExtraBold.otf",
    "/fonts/Nexa/NexaText-Trial-BookItalic.otf": "/fonts/Nexa/NexaText-Trial-BookItalic.otf",
    "/fonts/Nexa/NexaText-Trial-Book.otf": "/fonts/Nexa/NexaText-Trial-Book.otf",
    "/fonts/Nexa/NexaText-Trial-BoldItalic.otf": "/fonts/Nexa/NexaText-Trial-BoldItalic.otf",
    "/fonts/Nexa/NexaText-Trial-Bold.otf": "/fonts/Nexa/NexaText-Trial-Bold.otf",
    "/fonts/Nexa/NexaText-Trial-BlackItalic.otf": "/fonts/Nexa/NexaText-Trial-BlackItalic.otf",
    "/fonts/Nexa/NexaText-Trial-Black.otf": "/fonts/Nexa/NexaText-Trial-Black.otf",
    "/js/tom-select.complete.min.js": "/js/tom-select.complete.min.js",
    "/js/jquery-ui.js": "/js/jquery-ui.js",
    "/js/jquery-migrate-1.2.1.min.js": "/js/jquery-migrate-1.2.1.min.js",
    "/js/font-awesome-all.min.js": "/js/font-awesome-all.min.js",
    "/js/cdnjs.cloudflare.com_ajax_libs_slick-carousel_1.8.0_slick.min.js": "/js/cdnjs.cloudflare.com_ajax_libs_slick-carousel_1.8.0_slick.min.js",
    "/js/cdnjs.cloudflare.com_ajax_libs_jquery_1.12.0_jquery.min.js": "/js/cdnjs.cloudflare.com_ajax_libs_jquery_1.12.0_jquery.min.js",
    "/js/cdnjs.cloudflare.com_ajax_libs_OwlCarousel2_2.3.4_owl.carousel.min.js": "/js/cdnjs.cloudflare.com_ajax_libs_OwlCarousel2_2.3.4_owl.carousel.min.js",
    "/js/bootstrap.js": "/js/bootstrap.js",
    "/js/app.js": "/js/app.js"
}
